Metadata-Version: 1.1
Name: SiteLinksCheck
Version: 0.0.1
Summary: Given an url it returns all the links, broken links, internal links etc.
Home-page: https://github.com/Manideepto/SiteLinksCheck
Author: Manideepto
Author-email: dasmanideepto@gmail.com
License: MIT
Keywords: Broken Links,URL,Site Links Check
Platform: any
Classifier: Intended Audience :: Developers
Classifier: Natural Language :: English
Classifier: License :: OSI Approved :: MIT License
Classifier: Operating System :: OS Independent
Classifier: Programming Language :: Python
Classifier: Topic :: Utilities
